[{"_rid":"72f2dcdd-eab6-474a-bb0c-11eef25ef5eb","title":"ERP SUPPORT AND MAINTENANCE","categories":["Komputer/Teknologi Informasi","IT-Perangkat Lunak"],"type":"Penuh Waktu","url":"https://www.jobstreet.co.id/id/job/erp-support-and-maintenance-4329194","locations":["Jakarta Selatan"],"createdAt":"2023-05-11T04:49:48.000Z","salary":{"visible":false,"currency":"IDR","max":null,"min":null,"period":"monthly"},"company":{"name":"PT. Inti Talenta Teknologi","logo":"https://image-service-cdn.seek.com.au/87ca1637b93f34604261d3f8a76dbfcd009229de/ee4dce1061f3f616224767ad58cb2fc751b8d2dc","website":"","phone":null},"career":{"level":"Pegawai (non-manajemen & non-supervisor)","qualifications":["Sarjana (S1)","Diploma Pascasarjana","Gelar Professional","Magister (S2)"]},"benefit":["Tip","Waktu regular, Senin - Jumat","Bisnis (contoh: Kemeja)"]},{"_rid":"7cd8033c-d053-4051-9048-cec09f0721aa","title":"Junior Developer","categories":["Komputer/Teknologi Informasi","IT-Perangkat Lunak"],"type":"Penuh Waktu","url":"https://www.jobstreet.co.id/id/job/junior-developer-4329193","locations":["Jakarta Pusat"],"createdAt":"2023-05-11T04:49:28.000Z","salary":{"visible":false,"currency":"IDR","max":null,"min":null,"period":"monthly"},"company":{"name":"SAMORA GROUP","logo":"https://image-service-cdn.seek.com.au/8ee8703249293872f025649d857e6f7150f60f96/ee4dce1061f3f616224767ad58cb2fc751b8d2dc","website":"","phone":null},"career":{"level":"Pegawai (non-manajemen & non-supervisor)","qualifications":["Sarjana (S1)"]},"benefit":["Asuransi Gigi","Asuransi kesehatan","Penglihatan","Waktu regular, Senin - Jumat","Bisnis (contoh: Kemeja)","Maternity"]},{"_rid":"066c792a-740f-42bb-a032-2b6b57e0d028","title":"Software Quality Assurance Analyst","categories":["Komputer/Teknologi Informasi","IT-Perangkat Lunak"],"type":"Penuh Waktu","url":"https://www.jobstreet.co.id/id/job/software-quality-assurance-analyst-4329183","locations":["Jakarta Barat"],"createdAt":"2023-05-11T04:45:01.000Z","salary":{"visible":true,"currency":"IDR","max":"8500000","min":"6000000","period":"monthly"},"company":{"name":"PT Ako Media Asia","logo":"https://image-service-cdn.seek.com.au/0022fc11f4becc787c1138f2cceb86cbec0beef2/ee4dce1061f3f616224767ad58cb2fc751b8d2dc","website":"","phone":null},"career":{"level":"Pegawai (non-manajemen & non-supervisor)","qualifications":["Sarjana (S1)"]},"benefit":["Asuransi Gigi","Tunjangan Pendidikan","Tip","Asuransi kesehatan","Pinjaman","Penglihatan","Waktu regular, Senin - Jumat","Kasual (contoh: Kaos)"]},{"_rid":"e67ebfbc-9839-4156-8ab5-c70ed655ec3b","title":"IT Project Delivery Lead","categories":["Komputer/Teknologi Informasi","IT-Perangkat Lunak"],"type":"Penuh Waktu","url":"https://www.jobstreet.co.id/id/job/it-project-delivery-lead-4329177","locations":["Jakarta Selatan"],"createdAt":"2023-05-11T04:42:56.000Z","salary":{"visible":false,"currency":"IDR","max":null,"min":null,"period":"monthly"},"company":{"name":"PT KB Finansia Multi Finance","logo":"https://image-service-cdn.seek.com.au/ed6b5f2b90a5ab080f1516f403c8482cf0feea25/ee4dce1061f3f616224767ad58cb2fc751b8d2dc","website":"","phone":null},"career":{"level":"Supervisor/Koordinator","qualifications":["Sarjana (S1)"]},"benefit":["Asuransi Gigi","Asuransi kesehatan","Pinjaman","Parkir","Penglihatan","Waktu regular, Senin - Jumat","Bisnis (contoh: Kemeja)"]},{"_rid":"e19c0315-af3c-448f-8d3f-1efc9eec3563","title":"Senior/Lead Full Stack JavaScript Developer","categories":["Komputer/Teknologi Informasi","IT-Perangkat Lunak"],"type":"Penuh Waktu","url":"https://www.jobstreet.co.id/id/job/senior-lead-full-stack-javascript-developer-4329164","locations":["Jakarta Pusat"],"createdAt":"2023-05-11T04:39:34.000Z","salary":{"visible":false,"currency":"IDR","max":null,"min":null,"period":"monthly"},"company":{"name":"SOECHI GROUP","logo":"https://image-service-cdn.seek.com.au/d487b01d987a397cf145f30f7a54e8c4a3212f7a/ee4dce1061f3f616224767ad58cb2fc751b8d2dc","website":"","phone":null},"career":{"level":"Manajer/Asisten Manajer","qualifications":["Sertifikat Professional","D3 (Diploma)","D4 (Diploma)","Sarjana (S1)","Diploma Pascasarjana","Gelar Professional","Magister (S2)"]},"benefit":["Asuransi kesehatan","Parkir","Waktu regular, Senin - Jumat","Bisnis (contoh: Kemeja)"]},{"_rid":"0d64fac6-bc4a-43c5-90ce-cca1118ffdcc","title":"Frontend Developer","categories":["Komputer/Teknologi Informasi","IT-Perangkat Lunak"],"type":"Penuh Waktu","url":"https://www.jobstreet.co.id/id/job/frontend-developer-4329157","locations":["Jakarta Barat"],"createdAt":"2023-05-11T04:37:49.000Z","salary":{"visible":true,"currency":"IDR","max":"9000000","min":"7000000","period":"monthly"},"company":{"name":"PT Ako Media Asia","logo":"https://image-service-cdn.seek.com.au/0022fc11f4becc787c1138f2cceb86cbec0beef2/ee4dce1061f3f616224767ad58cb2fc751b8d2dc","website":"","phone":null},"career":{"level":"Pegawai (non-manajemen & non-supervisor)","qualifications":["Sarjana (S1)"]},"benefit":["Asuransi Gigi","Tunjangan Pendidikan","Tip","Asuransi kesehatan","Pinjaman","Penglihatan","Waktu regular, Senin - Jumat","Kasual (contoh: Kaos)"]},{"_rid":"cd857510-f03b-4cd5-a829-ccc7d39fa5e1","title":"IT Support","categories":["Komputer/Teknologi Informasi","IT-Admin Jaringan/Sistem/Database"],"type":"Penuh Waktu","url":"https://www.jobstreet.co.id/id/job/it-support-4329134","locations":["Jakarta Raya"],"createdAt":"2023-05-11T04:31:08.000Z","salary":{"visible":false,"currency":"IDR","max":null,"min":null,"period":"monthly"},"company":{"name":"PT Karya Solusi Prima Sejahtera","logo":"https://image-service-cdn.seek.com.au/bb0f2c313297f2db3d497466b95d7da85644edc0/ee4dce1061f3f616224767ad58cb2fc751b8d2dc","website":"","phone":null},"career":{"level":"Pegawai (non-manajemen & non-supervisor)","qualifications":["Sertifikat Professional","D3 (Diploma)","D4 (Diploma)","Sarjana (S1)"]},"benefit":["Asuransi Gigi","Asuransi kesehatan","Waktu regular, Senin - Jumat","Formil (contoh: Kemeja + Dasi)"]},{"_rid":"69a18fd0-e9a9-45db-9678-3660d87732db","title":"IT Programmer","categories":["Komputer/Teknologi Informasi","IT-Perangkat Lunak"],"type":"Kontrak","url":"https://www.jobstreet.co.id/id/job/it-programmer-4329121","locations":["Surabaya"],"createdAt":"2023-05-11T04:27:59.000Z","salary":{"visible":false,"currency":"IDR","max":null,"min":null,"period":"monthly"},"company":{"name":"PT Warna Warni Media","logo":"https://image-service-cdn.seek.com.au/7f25c1b972638bfea2568107babb97676a214e76/ee4dce1061f3f616224767ad58cb2fc751b8d2dc","website":"","phone":null},"career":{"level":"Pegawai (non-manajemen & non-supervisor)","qualifications":["Sertifikat Professional","D3 (Diploma)","D4 (Diploma)","Sarjana (S1)"]},"benefit":["Asuransi Gigi","Asuransi kesehatan","Formil (contoh: Kemeja + Dasi)","Mondays-Saturdays"]},{"_rid":"c7120fc3-d4a3-4ec5-9754-a78b85a0ca60","title":"Phyton Developer","categories":["Komputer/Teknologi Informasi","IT-Perangkat Lunak"],"type":"Penuh Waktu","url":"https://www.jobstreet.co.id/id/job/phyton-developer-4329053","locations":["Jakarta Raya"],"createdAt":"2023-05-11T04:13:19.000Z","salary":{"visible":false,"currency":"IDR","max":null,"min":null,"period":"monthly"},"company":{"name":"PT Rapid Teknologi Indonesia","logo":"https://image-service-cdn.seek.com.au/3d0b7dc5bd2f1f173f0c86f6cd7a1d5efc19003a/ee4dce1061f3f616224767ad58cb2fc751b8d2dc","website":"","phone":null},"career":{"level":"Pegawai (non-manajemen & non-supervisor)","qualifications":["Sarjana (S1)"]},"benefit":["Tip","Asuransi kesehatan","Waktu regular, Senin - Jumat","Bisnis (contoh: Kemeja)"]},{"_rid":"deec1af1-06c5-498c-bc4f-62e09d91996d","title":"IT ASP.Net","categories":["Komputer/Teknologi Informasi","IT-Perangkat Lunak"],"type":"Penuh Waktu","url":"https://www.jobstreet.co.id/id/job/it-asp.net-4329031","locations":["Jakarta Raya"],"createdAt":"2023-05-11T04:06:14.000Z","salary":{"visible":true,"currency":"IDR","max":"8000000","min":"7000000","period":"monthly"},"company":{"name":"PT Valdo Sumber Daya Mandiri","logo":"https://image-service-cdn.seek.com.au/c8b4653eeb66df10a0b4efb696f683ada8224d5a/ee4dce1061f3f616224767ad58cb2fc751b8d2dc","website":"","phone":null},"career":{"level":"Lulusan baru/Pengalaman kerja kurang dari 1 tahun","qualifications":["Sarjana (S1)"]},"benefit":[]},{"_rid":"17c1dbb9-2044-4e10-bdfb-0953809a4c99","title":"DATA SCIENTIST","categories":["Komputer/Teknologi Informasi","IT-Perangkat Lunak"],"type":"Penuh Waktu","url":"https://www.jobstreet.co.id/id/job/data-scientist-4329023","locations":["Jakarta Barat"],"createdAt":"2023-05-11T04:03:21.000Z","salary":{"visible":false,"currency":"IDR","max":null,"min":null,"period":"monthly"},"company":{"name":"PT Mega Central Finance","logo":"https://image-service-cdn.seek.com.au/5a3af6aef73aefc68566a4c26b6f9b36cb214c9e/ee4dce1061f3f616224767ad58cb2fc751b8d2dc","website":"","phone":null},"career":{"level":"Pegawai (non-manajemen & non-supervisor)","qualifications":["Sarjana (S1)"]},"benefit":["Asuransi kesehatan","Parkir","Formil (contoh: Kemeja + Dasi)","Head Office: Senin - Jumat"]},{"_rid":"7df968ed-e1ca-4f7a-b5c3-688a0cf561cb","title":"Senior UI/UX Designer","categories":["Komputer/Teknologi Informasi","IT-Perangkat Lunak"],"type":"Penuh Waktu","url":"https://www.jobstreet.co.id/id/job/senior-ui-ux-designer-4329011","locations":["Jakarta Raya"],"createdAt":"2023-05-11T04:00:35.000Z","salary":{"visible":false,"currency":"IDR","max":null,"min":null,"period":"monthly"},"company":{"name":"SOECHI GROUP","logo":"https://image-service-cdn.seek.com.au/d487b01d987a397cf145f30f7a54e8c4a3212f7a/ee4dce1061f3f616224767ad58cb2fc751b8d2dc","website":"","phone":null},"career":{"level":"Supervisor/Koordinator","qualifications":["Sertifikat Professional","D3 (Diploma)","D4 (Diploma)","Sarjana (S1)","Diploma Pascasarjana","Gelar Professional","Magister (S2)"]},"benefit":["Asuransi kesehatan","Parkir","Waktu regular, Senin - Jumat","Bisnis (contoh: Kemeja)"]},{"_rid":"50703463-8516-4170-81d4-5d1be130c304","title":"Programmer","categories":["Komputer/Teknologi Informasi","IT-Perangkat Lunak"],"type":"Penuh Waktu","url":"https://www.jobstreet.co.id/id/job/programmer-4328993","locations":["Semarang"],"createdAt":"2023-05-11T03:55:06.000Z","salary":{"visible":false,"currency":"IDR","max":null,"min":null,"period":"monthly"},"company":{"name":"izzaweb","logo":"https://image-service-cdn.seek.com.au/39b3b88006a9610896bd8814286fa7a8775337f0/ee4dce1061f3f616224767ad58cb2fc751b8d2dc","website":"","phone":null},"career":{"level":"Pegawai (non-manajemen & non-supervisor)","qualifications":["SMA","SMU/SMK/STM","Sertifikat Professional","D3 (Diploma)","D4 (Diploma)","Sarjana (S1)"]},"benefit":["Waktu regular, Senin - Jumat","Kasual (contoh: Kaos)"]},{"_rid":"1ab2b460-ffe5-49f2-8f5b-1c56e4e3e066","title":"SENIOR DevOps Eng","categories":["Komputer/Teknologi Informasi","IT-Perangkat Lunak"],"type":"Penuh Waktu","url":"https://www.jobstreet.co.id/id/job/senior-devops-eng-4328989","locations":["Jakarta Barat"],"createdAt":"2023-05-11T03:54:30.000Z","salary":{"visible":true,"currency":"IDR","max":"20000000","min":"10000000","period":"monthly"},"company":{"name":"PT. ALPHA INDO SOFT","logo":"https://image-service-cdn.seek.com.au/46fa204c6bc9269d2a5cd25196418feea423ae88/ee4dce1061f3f616224767ad58cb2fc751b8d2dc","website":"","phone":null},"career":{"level":"Pegawai (non-manajemen & non-supervisor)","qualifications":["Sertifikat Professional","D3 (Diploma)","D4 (Diploma)","Sarjana (S1)","Diploma Pascasarjana","Gelar Professional","Magister (S2)"]},"benefit":["Tunjangan Pendidikan","Tip","Olahraga (contoh: pusat kebugaran)","Parkir","Formil (contoh: Kemeja + Dasi)"]},{"_rid":"3971bcc0-d619-474e-8bfa-6163ab017f14","title":"IOS Developer","categories":["Komputer/Teknologi Informasi","IT-Perangkat Lunak"],"type":"Penuh Waktu","url":"https://www.jobstreet.co.id/id/job/ios-developer-4328988","locations":["Jakarta Pusat"],"createdAt":"2023-05-11T03:54:29.000Z","salary":{"visible":false,"currency":"IDR","max":null,"min":null,"period":"monthly"},"company":{"name":"","logo":null,"website":"","phone":null},"career":{"level":"Manajer/Asisten Manajer","qualifications":["Sarjana (S1)"]},"benefit":[]},{"_rid":"c6c53311-b213-48d3-bed0-f09dd71efed4","title":"Data Center Manager","categories":["Komputer/Teknologi Informasi","IT-Admin Jaringan/Sistem/Database"],"type":"Penuh Waktu","url":"https://www.jobstreet.co.id/id/job/data-center-manager-4328972","locations":["Tangerang"],"createdAt":"2023-05-11T03:50:14.000Z","salary":{"visible":true,"currency":"IDR","max":"20000000","min":"17000000","period":"monthly"},"company":{"name":"PT Visionet Data Internasional","logo":"https://image-service-cdn.seek.com.au/84d23b3586ee4efd70ea62878095fcc6b1639e33/ee4dce1061f3f616224767ad58cb2fc751b8d2dc","website":"","phone":null},"career":{"level":"Manajer/Asisten Manajer","qualifications":["Sarjana (S1)"]},"benefit":["Asuransi kesehatan","Waktu regular, Senin - Jumat","Formil (contoh: Kemeja + Dasi)"]},{"_rid":"0283b41c-7ebc-4a67-8080-8f1ca487e383","title":"IT Support","categories":["Komputer/Teknologi Informasi","IT-Admin Jaringan/Sistem/Database"],"type":"Penuh Waktu","url":"https://www.jobstreet.co.id/id/job/it-support-4328959","locations":["Jakarta Barat"],"createdAt":"2023-05-11T03:47:09.000Z","salary":{"visible":false,"currency":"IDR","max":null,"min":null,"period":"monthly"},"company":{"name":"Barantum","logo":"https://image-service-cdn.seek.com.au/084c8f8e598f5489b3f864676e794703d2cba8cd/ee4dce1061f3f616224767ad58cb2fc751b8d2dc","website":"","phone":null},"career":{"level":"Pegawai (non-manajemen & non-supervisor)","qualifications":["Sertifikat Professional","D3 (Diploma)","D4 (Diploma)","Sarjana (S1)"]},"benefit":["Asuransi kesehatan","Olahraga (contoh: pusat kebugaran)","Parkir","Penglihatan","Waktu regular, Senin - Jumat","Bisnis (contoh: Kemeja)","Insentive, Bonusses"]},{"_rid":"708c2b37-46c1-4556-991b-6503141e6b5d","title":"HOST LIVE TIKTOK","categories":["Penjualan / Pemasaran","E-commerce"],"type":"Penuh Waktu","url":"https://www.jobstreet.co.id/id/job/host-live-tiktok-4328958","locations":["Jakarta Raya"],"createdAt":"2023-05-11T03:46:49.000Z","salary":{"visible":false,"currency":"IDR","max":null,"min":null,"period":"monthly"},"company":{"name":"PT Digital Film Media","logo":"https://image-service-cdn.seek.com.au/4338312757faa7197b78b28f7ddfedc54a1f0260/ee4dce1061f3f616224767ad58cb2fc751b8d2dc","website":"","phone":null},"career":{"level":"Pegawai (non-manajemen & non-supervisor)","qualifications":["Sertifikat Professional","D3 (Diploma)","D4 (Diploma)","Sarjana (S1)"]},"benefit":["Waktu regular, Senin - Jumat","interesting allowance","Casual or Business"]},{"_rid":"2312d1bd-943d-48e5-9194-79a87297cb20","title":"Senior Test Engineer","categories":["Komputer/Teknologi Informasi","IT-Perangkat Lunak"],"type":"Penuh Waktu","url":"https://www.jobstreet.co.id/id/job/senior-test-engineer-4328932","locations":["Kepulauan Riau"],"createdAt":"2023-05-11T03:41:30.000Z","salary":{"visible":true,"currency":"IDR","max":"10000000","min":"8000000","period":"monthly"},"company":{"name":"PT Reeracoen Indonesia","logo":"https://image-service-cdn.seek.com.au/d33bd8dd71322db8ea58cab3a99c9a2f44aec216/ee4dce1061f3f616224767ad58cb2fc751b8d2dc","website":"","phone":null},"career":{"level":"Pegawai (non-manajemen & non-supervisor)","qualifications":["Sertifikat Professional","D3 (Diploma)","D4 (Diploma)","Sarjana (S1)","Diploma Pascasarjana","Gelar Professional","Magister (S2)"]},"benefit":["Tip","Asuransi kesehatan","Waktu regular, Senin - Jumat","Bisnis (contoh: Kemeja)"]},{"_rid":"14f63a93-26ce-46a9-8455-9288fe62443d","title":"IT Project Management Officer (PMO)","categories":["Komputer/Teknologi Informasi","IT-Perangkat Lunak"],"type":"Penuh Waktu","url":"https://www.jobstreet.co.id/id/job/it-project-management-officer-pmo-4328904","locations":["Jakarta Raya"],"createdAt":"2023-05-11T03:35:58.000Z","salary":{"visible":true,"currency":"IDR","max":"28000000","min":"22000000","period":"monthly"},"company":{"name":"PT Valdo Sumber Daya Mandiri","logo":"https://image-service-cdn.seek.com.au/c8b4653eeb66df10a0b4efb696f683ada8224d5a/ee4dce1061f3f616224767ad58cb2fc751b8d2dc","website":"","phone":null},"career":{"level":"Supervisor/Koordinator","qualifications":["Sarjana (S1)"]},"benefit":[]},{"_rid":"c2a7c730-d2bc-4033-8f96-3faac3a523a2","title":"BI Developer Engineer","categories":["Komputer/Teknologi Informasi","IT-Perangkat Lunak"],"type":"Penuh Waktu","url":"https://www.jobstreet.co.id/id/job/bi-developer-engineer-4328900","locations":["Kepulauan Riau"],"createdAt":"2023-05-11T03:34:45.000Z","salary":{"visible":true,"currency":"IDR","max":"10000000","min":"8000000","period":"monthly"},"company":{"name":"PT Reeracoen Indonesia","logo":"https://image-service-cdn.seek.com.au/d33bd8dd71322db8ea58cab3a99c9a2f44aec216/ee4dce1061f3f616224767ad58cb2fc751b8d2dc","website":"","phone":null},"career":{"level":"Pegawai (non-manajemen & non-supervisor)","qualifications":["Sertifikat Professional","D3 (Diploma)","D4 (Diploma)","Sarjana (S1)","Diploma Pascasarjana","Gelar Professional","Magister (S2)"]},"benefit":["Tip","Asuransi kesehatan","Waktu regular, Senin - Jumat","Bisnis (contoh: Kemeja)"]},{"_rid":"d7402235-6807-4bac-a01f-dfef5cb14a46","title":"System Analyst","categories":["Komputer/Teknologi Informasi","IT-Perangkat Lunak"],"type":"Penuh Waktu","url":"https://www.jobstreet.co.id/id/job/system-analyst-4328894","locations":["Jawa Tengah"],"createdAt":"2023-05-11T03:32:58.000Z","salary":{"visible":false,"currency":"IDR","max":null,"min":null,"period":"monthly"},"company":{"name":"PT VISIONE SISTEM","logo":"https://image-service-cdn.seek.com.au/1a4d65eb7b1ec9cb817faf4fce37d5bfbc2eabe3/ee4dce1061f3f616224767ad58cb2fc751b8d2dc","website":"","phone":null},"career":{"level":"Pegawai (non-manajemen & non-supervisor)","qualifications":["SMA","SMU/SMK/STM","Sertifikat Professional","D3 (Diploma)","D4 (Diploma)"]},"benefit":[]},{"_rid":"0aede569-8a9b-4c25-9dfe-a2cdf4fab2f5","title":"QUALITY ASSURANCE / QA","categories":["Komputer/Teknologi Informasi","IT-Perangkat Lunak"],"type":"Penuh Waktu","url":"https://www.jobstreet.co.id/id/job/quality-assurance-qa-4328875","locations":["Jakarta Utara"],"createdAt":"2023-05-11T03:27:36.000Z","salary":{"visible":true,"currency":"IDR","max":"10000000","min":"6500000","period":"monthly"},"company":{"name":"PT Arta Plastika Mandiri","logo":"https://image-service-cdn.seek.com.au/4edf153a4f9bb589b0c240d9dd1a206585b9d9eb/ee4dce1061f3f616224767ad58cb2fc751b8d2dc","website":"","phone":null},"career":{"level":"Supervisor/Koordinator","qualifications":["Sertifikat Professional","D3 (Diploma)","D4 (Diploma)","Sarjana (S1)"]},"benefit":["Asuransi kesehatan","Bisnis (contoh: Kemeja)","Senin-Sabtu"]},{"_rid":"cf94ea17-7c3e-4040-a476-64e950a5efed","title":"Business System Analyst","categories":["Komputer/Teknologi Informasi","IT-Perangkat Lunak"],"type":"Penuh Waktu","url":"https://www.jobstreet.co.id/id/job/business-system-analyst-4328872","locations":["Jakarta Raya"],"createdAt":"2023-05-11T03:26:22.000Z","salary":{"visible":false,"currency":"IDR","max":null,"min":null,"period":"monthly"},"company":{"name":"MODENA INDONESIA","logo":"https://image-service-cdn.seek.com.au/f805f06469953c982303363c2105eb7eff35d8a8/ee4dce1061f3f616224767ad58cb2fc751b8d2dc","website":"","phone":null},"career":{"level":"Pegawai (non-manajemen & non-supervisor)","qualifications":["Sarjana (S1)"]},"benefit":["Asuransi Gigi","Tunjangan Pendidikan","Tip","Asuransi kesehatan","Pinjaman","Penglihatan","Waktu regular, Senin - Jumat","Kasual (contoh: Kaos)"]},{"_rid":"35b3f949-2a32-47ee-88b8-b81335b9a598","title":"Full Stack Developer","categories":["Komputer/Teknologi Informasi","IT-Perangkat Lunak"],"type":"Penuh Waktu","url":"https://www.jobstreet.co.id/id/job/full-stack-developer-4328848","locations":["Jakarta Pusat"],"createdAt":"2023-05-11T03:20:21.000Z","salary":{"visible":false,"currency":"IDR","max":null,"min":null,"period":"monthly"},"company":{"name":"PT. Berca Hardayaperkasa","logo":"https://image-service-cdn.seek.com.au/6a76252207cfed561e664c874d4631f4aefd8409/ee4dce1061f3f616224767ad58cb2fc751b8d2dc","website":"","phone":null},"career":{"level":"Pegawai (non-manajemen & non-supervisor)","qualifications":["Sertifikat Professional","D3 (Diploma)","D4 (Diploma)","Sarjana (S1)"]},"benefit":["Tip","Asuransi kesehatan","Waktu regular, Senin - Jumat","Bisnis (contoh: Kemeja)"]},{"_rid":"f0859a77-8f5b-4c9c-83b4-fb8f479d8973","title":"Host live stremer tiktok","categories":["Penjualan / Pemasaran","E-commerce"],"type":"Penuh Waktu","url":"https://www.jobstreet.co.id/id/job/host-live-stremer-tiktok-4328844","locations":["Jakarta Pusat"],"createdAt":"2023-05-11T03:19:37.000Z","salary":{"visible":true,"currency":"IDR","max":"4000000","min":"2000000","period":"monthly"},"company":{"name":"PT COOL VISION INDONESIA","logo":null,"website":"","phone":null},"career":{"level":"Pegawai (non-manajemen & non-supervisor)","qualifications":["Tidak terspesifikasi"]},"benefit":[]},{"_rid":"d1c2e1d9-0210-444b-959b-ed5b75c34cbe","title":"ERP Project Manager","categories":["Komputer/Teknologi Informasi","IT-Perangkat Lunak"],"type":"Penuh Waktu","url":"https://www.jobstreet.co.id/id/job/erp-project-manager-4328833","locations":["Jakarta Barat"],"createdAt":"2023-05-11T03:17:16.000Z","salary":{"visible":false,"currency":"IDR","max":null,"min":null,"period":"monthly"},"company":{"name":"Geekhunter","logo":"https://image-service-cdn.seek.com.au/9b1ac08312d45d7e6f0965d6cfa215d52017a644/ee4dce1061f3f616224767ad58cb2fc751b8d2dc","website":"","phone":null},"career":{"level":"Manajer/Asisten Manajer","qualifications":["Sarjana (S1)","Diploma Pascasarjana","Gelar Professional","Magister (S2)"]},"benefit":["Asuransi kesehatan","Waktu regular, Senin - Jumat","Kasual (contoh: Kaos)"]},{"_rid":"aad81f56-0ec8-4457-b832-fbe49733e3ee","title":"OPERATION DEVELOPMENT PROGRAM","categories":["Penjualan / Pemasaran","E-commerce"],"type":"Penuh Waktu","url":"https://www.jobstreet.co.id/id/job/operation-development-program-4328799","locations":["Jawa Tengah"],"createdAt":"2023-05-11T03:09:44.000Z","salary":{"visible":false,"currency":"IDR","max":null,"min":null,"period":"monthly"},"company":{"name":"Barberking indonesia","logo":"https://image-service-cdn.seek.com.au/0e9583599817f65f05155f835dfa3c87cb94afcf/ee4dce1061f3f616224767ad58cb2fc751b8d2dc","website":"","phone":null},"career":{"level":"Lulusan baru/Pengalaman kerja kurang dari 1 tahun","qualifications":["Sertifikat Professional","D3 (Diploma)","D4 (Diploma)"]},"benefit":[]},{"_rid":"79c1458c-1e00-4733-8f00-fb73a48d2986","title":"Network Engineer","categories":["Komputer/Teknologi Informasi","IT-Admin Jaringan/Sistem/Database"],"type":"Penuh Waktu","url":"https://www.jobstreet.co.id/id/job/network-engineer-4328798","locations":["Jakarta Raya"],"createdAt":"2023-05-11T03:09:23.000Z","salary":{"visible":false,"currency":"IDR","max":null,"min":null,"period":"monthly"},"company":{"name":"PT. Orbit Nasional Edukasi","logo":"https://image-service-cdn.seek.com.au/b2b376bcc33466fd943bb4de08665eaa2b866ce5/ee4dce1061f3f616224767ad58cb2fc751b8d2dc","website":"","phone":null},"career":{"level":"Pegawai (non-manajemen & non-supervisor)","qualifications":["Sertifikat Professional","D3 (Diploma)","D4 (Diploma)","Sarjana (S1)"]},"benefit":["Tunjangan Pendidikan","Tip","Asuransi kesehatan","Pinjaman","Waktu regular, Senin - Jumat","Kasual (contoh: Kaos)"]},{"_rid":"3fa97772-316c-4e6a-bedc-4a524c90fe20","title":"Java Developer","categories":["Komputer/Teknologi Informasi","IT-Perangkat Lunak"],"type":"Penuh Waktu","url":"https://www.jobstreet.co.id/id/job/java-developer-4328790","locations":["Jakarta Raya"],"createdAt":"2023-05-11T03:07:30.000Z","salary":{"visible":false,"currency":"IDR","max":null,"min":null,"period":"monthly"},"company":{"name":"PT Asuransi Jiwa Astra","logo":"https://image-service-cdn.seek.com.au/6a2263767506bdebccc5cab880f54bf5fe0e205d/ee4dce1061f3f616224767ad58cb2fc751b8d2dc","website":"","phone":null},"career":{"level":"Manajer/Asisten Manajer","qualifications":["Sarjana (S1)"]},"benefit":["Tip","Asuransi kesehatan","Waktu regular, Senin - Jumat","BPJS, Bonus Tahunan, Program Reward, THR, Komisi (Sales)","Formal and Casual"]}]