[{"_rid":"7cc4920c-1201-4f18-bcd6-e0a9eecba45f","title":"Junior Software Developer","categories":["Komputer/Teknologi Informasi","IT-Perangkat Lunak"],"type":"Penuh Waktu","url":"https://www.jobstreet.co.id/id/job/junior-software-developer-4493584","locations":["Jawa Timur"],"createdAt":"2023-10-09T14:25:31.000Z","salary":{"visible":true,"currency":"IDR","max":"5000000","min":"2500000","period":"monthly"},"company":{"name":"PT Tim Teknologi Global","logo":"https://image-service-cdn.seek.com.au/cd211806827c58bda99717f02b3686f0a6b8aadb/ee4dce1061f3f616224767ad58cb2fc751b8d2dc","website":"","phone":null},"career":{"level":"Pegawai (non-manajemen & non-supervisor)","qualifications":["SMA","SMU/SMK/STM","Sertifikat Professional","D3 (Diploma)","D4 (Diploma)","Sarjana (S1)"]},"benefit":["Waktu regular, Senin - Jumat","Kasual (contoh: Kaos)"]},{"_rid":"9c7644a6-2942-428e-85f6-94115b2f43bd","title":"Game Developer ( Mobile HTML5 / Web / Multiplayer / Programmer )","categories":["Komputer/Teknologi Informasi","IT-Perangkat Lunak"],"type":"Penuh Waktu","url":"https://www.jobstreet.co.id/id/job/game-developer-mobile-html5-web-multiplayer-programmer-5551698/origin/my","locations":["Aceh","Jakarta Raya","Jawa Barat","Jawa Tengah","Jawa Timur","Nusa Tenggara Barat","Nusa Tenggara Timur","Sulawesi Selatan","Sumatera Selatan","Sumatera Utara"],"createdAt":"2023-10-09T14:00:09.000Z","salary":{"visible":true,"currency":"IDR","max":"8000000","min":"4000000","period":"monthly"},"company":{"name":"Impact360 Solutions Sdn Bhd","logo":"https://image-service-cdn.seek.com.au/cedff589ebe9d852a33989a35efb7fc721ea237a/ee4dce1061f3f616224767ad58cb2fc751b8d2dc","website":"","phone":null},"career":{"level":"Lulusan baru/Pengalaman kerja kurang dari 1 tahun","qualifications":["D3 (Diploma)","D4 (Diploma)","Sarjana (S1)","Diploma Pascasarjana","Gelar Professional"]},"benefit":["Waktu regular, Senin - Jumat","Kasual (contoh: Kaos)"]},{"_rid":"b2507922-bf32-457a-84b5-347c5eacff4a","title":"Web Developer","categories":["Komputer/Teknologi Informasi","IT-Perangkat Lunak"],"type":"Penuh Waktu","url":"https://www.jobstreet.co.id/id/job/web-developer-4493543","locations":["Yogyakarta"],"createdAt":"2023-10-09T12:30:43.000Z","salary":{"visible":false,"currency":"IDR","max":null,"min":null,"period":"monthly"},"company":{"name":"PT Lentera Software Indonesia","logo":"https://image-service-cdn.seek.com.au/91d21c84de0848d6a3d196b3a5bfd8e060a48d15/ee4dce1061f3f616224767ad58cb2fc751b8d2dc","website":"","phone":null},"career":{"level":"Lulusan baru/Pengalaman kerja kurang dari 1 tahun","qualifications":["Tidak terspesifikasi"]},"benefit":["Asuransi kesehatan","Parkir","Kasual (contoh: Kaos)"]},{"_rid":"95ce8678-359f-4484-8f62-5c0ee5e65caa","title":"SAP ABAP, SAP FI & SM Consultant","categories":["Komputer/Teknologi Informasi","IT-Perangkat Lunak"],"type":"Kontrak","url":"https://www.jobstreet.co.id/id/job/sap-abap-sap-fi-sm-consultant-4493554","locations":["Jakarta Utara"],"createdAt":"2023-10-09T11:55:44.000Z","salary":{"visible":true,"currency":"IDR","max":"20000000","min":"15000000","period":"monthly"},"company":{"name":"PT Rsystems Ibizcs International","logo":"https://image-service-cdn.seek.com.au/29aec1768cc0711dc8157b2d5c9cf793882449ab/ee4dce1061f3f616224767ad58cb2fc751b8d2dc","website":"","phone":null},"career":{"level":"Pegawai (non-manajemen & non-supervisor)","qualifications":["Sarjana (S1)"]},"benefit":[]},{"_rid":"d03ea6df-8c17-4e4f-8c8a-894eb5cab7d9","title":"Audit-Akunting Junior to Senior Level","categories":["Komputer/Teknologi Informasi","IT-Perangkat Lunak"],"type":"Penuh Waktu","url":"https://www.jobstreet.co.id/id/job/audit-akunting-junior-to-senior-level-4493537","locations":["Jakarta Pusat"],"createdAt":"2023-10-09T11:29:25.000Z","salary":{"visible":false,"currency":"IDR","max":null,"min":null,"period":"monthly"},"company":{"name":"LF Consulting","logo":"https://image-service-cdn.seek.com.au/d12e1557dc90fdffca808604fdcfc7addbbd1d03/ee4dce1061f3f616224767ad58cb2fc751b8d2dc","website":"","phone":null},"career":{"level":"Pegawai (non-manajemen & non-supervisor)","qualifications":["Sarjana (S1)"]},"benefit":["Asuransi kesehatan","Waktu regular, Senin - Jumat","Bisnis (contoh: Kemeja)"]},{"_rid":"11b1a5db-e0ba-4dbd-a6bf-af1189bcaebc","title":"E-COMMERCE SALES MANAGER / HEAD OF SALES E-COMMERCE / MARKETPLACE / ONLINE SHOP","categories":["Penjualan / Pemasaran","E-commerce"],"type":"Penuh Waktu","url":"https://www.jobstreet.co.id/id/job/e-commerce-sales-manager-head-of-sales-e-commerce-marketplace-online-shop-4493522","locations":["Jakarta Barat"],"createdAt":"2023-10-09T11:10:37.000Z","salary":{"visible":false,"currency":"IDR","max":null,"min":null,"period":"monthly"},"company":{"name":"PT Mega Ponsel Indonesia","logo":"https://image-service-cdn.seek.com.au/4072597d84dc6f21fdc8f9788cbca3b9fe1c5fb2/ee4dce1061f3f616224767ad58cb2fc751b8d2dc","website":"","phone":null},"career":{"level":"Manajer/Asisten Manajer","qualifications":["Sarjana (S1)"]},"benefit":["Pinjaman","Parkir","Kasual (contoh: Kaos)","Mondays - Saturdays"]},{"_rid":"f21731a4-6e8c-4ba6-8a36-a34ef8778e66","title":"System and Network Administrator","categories":["Komputer/Teknologi Informasi","IT-Admin Jaringan/Sistem/Database"],"type":"Penuh Waktu","url":"https://www.jobstreet.co.id/id/job/system-and-network-administrator-4493498","locations":["Tangerang"],"createdAt":"2023-10-09T10:43:49.000Z","salary":{"visible":false,"currency":"IDR","max":null,"min":null,"period":"monthly"},"company":{"name":"PT Square Gate One / ESPAY.ID","logo":"https://image-service-cdn.seek.com.au/823d49bee8d79aadf0dcf90efde4e928b11c6f19/ee4dce1061f3f616224767ad58cb2fc751b8d2dc","website":"","phone":null},"career":{"level":"Pegawai (non-manajemen & non-supervisor)","qualifications":["Sertifikat Professional","D3 (Diploma)","D4 (Diploma)","Sarjana (S1)"]},"benefit":["Asuransi Gigi","Tip","Asuransi kesehatan","Parkir","Waktu regular, Senin - Jumat","Kasual (contoh: Kaos)"]},{"_rid":"427aaa95-64fe-4249-8d17-2390b034052b","title":"IT Programmer","categories":["Komputer/Teknologi Informasi","IT-Perangkat Lunak"],"type":"Penuh Waktu","url":"https://www.jobstreet.co.id/id/job/it-programmer-4493491","locations":["Surakarta"],"createdAt":"2023-10-09T10:38:47.000Z","salary":{"visible":false,"currency":"IDR","max":null,"min":null,"period":"monthly"},"company":{"name":"PT Citra Warna Abadi (Solo)","logo":"https://image-service-cdn.seek.com.au/2f6701e5b72abedae22f47e92db48f3b737e19da/ee4dce1061f3f616224767ad58cb2fc751b8d2dc","website":"","phone":null},"career":{"level":"Pegawai (non-manajemen & non-supervisor)","qualifications":["SMA","SMU/SMK/STM","Sertifikat Professional","D3 (Diploma)","D4 (Diploma)","Sarjana (S1)"]},"benefit":["Tip","Asuransi kesehatan","Pinjaman","Bisnis (contoh: Kemeja)"]},{"_rid":"09a8f4f6-347d-4913-99b8-a824a8c2e53e","title":"Manager OnLine Shop","categories":["Penjualan / Pemasaran","E-commerce"],"type":"Penuh Waktu","url":"https://www.jobstreet.co.id/id/job/manager-online-shop-4491405","locations":["Jakarta Utara"],"createdAt":"2023-10-09T10:09:14.000Z","salary":{"visible":true,"currency":"IDR","max":"11000000","min":"10000000","period":"monthly"},"company":{"name":"PT. HARUM SEMESTA DAITIA","logo":"https://image-service-cdn.seek.com.au/78c761fdfd87f3833609a216215b7fa377c2a4dc/ee4dce1061f3f616224767ad58cb2fc751b8d2dc","website":"","phone":null},"career":{"level":"Manajer/Asisten Manajer","qualifications":["Sarjana (S1)"]},"benefit":[]},{"_rid":"c950ae62-7f10-4fbd-a748-2dd4c2d266b3","title":"IT Support","categories":["Komputer/Teknologi Informasi","IT-Admin Jaringan/Sistem/Database"],"type":"Penuh Waktu","url":"https://www.jobstreet.co.id/id/job/it-support-4493428","locations":["Jakarta Utara"],"createdAt":"2023-10-09T10:07:40.000Z","salary":{"visible":false,"currency":"IDR","max":null,"min":null,"period":"monthly"},"company":{"name":"LIECO GROUP","logo":"https://image-service-cdn.seek.com.au/befced9f9d9dead0cf518ec7a18e952adf9be35d/ee4dce1061f3f616224767ad58cb2fc751b8d2dc","website":"","phone":null},"career":{"level":"Pegawai (non-manajemen & non-supervisor)","qualifications":["Sarjana (S1)"]},"benefit":["Waktu regular, Senin - Jumat","Bisnis (contoh: Kemeja)","Others Benefits"]},{"_rid":"a6e95e90-ce5a-446c-bd1c-da8fee1616b3","title":"IT Quality Assurance (Testing)","categories":["Komputer/Teknologi Informasi","IT-Perangkat Lunak"],"type":"Penuh Waktu","url":"https://www.jobstreet.co.id/id/job/it-quality-assurance-testing-4493418","locations":["Tangerang"],"createdAt":"2023-10-09T10:04:08.000Z","salary":{"visible":false,"currency":"IDR","max":null,"min":null,"period":"monthly"},"company":{"name":"PT Lippo General Insurance Tbk","logo":"https://image-service-cdn.seek.com.au/61f18c58d8f6b61995a332956066dd2ca709d289/ee4dce1061f3f616224767ad58cb2fc751b8d2dc","website":"","phone":null},"career":{"level":"Pegawai (non-manajemen & non-supervisor)","qualifications":["Sertifikat Professional","D3 (Diploma)","D4 (Diploma)","Sarjana (S1)"]},"benefit":["Asuransi Gigi","Tunjangan Pendidikan","Tip","Asuransi kesehatan","Olahraga (contoh: pusat kebugaran)","Penglihatan","Waktu regular, Senin - Jumat","Bisnis (contoh: Kemeja)","THR, Bonus"]},{"_rid":"4ec69c2d-a2f1-43d4-af16-cfdba8679a49","title":"IT STAFF","categories":["Komputer/Teknologi Informasi","IT-Admin Jaringan/Sistem/Database"],"type":"Penuh Waktu","url":"https://www.jobstreet.co.id/id/job/it-staff-4493412","locations":["Tangerang"],"createdAt":"2023-10-09T10:01:39.000Z","salary":{"visible":false,"currency":"IDR","max":null,"min":null,"period":"monthly"},"company":{"name":"PT Varley Indonesia","logo":"https://image-service-cdn.seek.com.au/9321aece9210dbacbadf625ff3146cdf000f74a3/ee4dce1061f3f616224767ad58cb2fc751b8d2dc","website":"","phone":null},"career":{"level":"Pegawai (non-manajemen & non-supervisor)","qualifications":["Sertifikat Professional","D3 (Diploma)","D4 (Diploma)","Sarjana (S1)"]},"benefit":["Waktu regular, Senin - Jumat"]},{"_rid":"b18836cb-c3a0-4117-b7fa-eea59b92cf02","title":"PHP Laravel Developer","categories":["Komputer/Teknologi Informasi","IT-Perangkat Lunak"],"type":"Penuh Waktu","url":"https://www.jobstreet.co.id/id/job/php-laravel-developer-4493392","locations":["Jakarta Timur"],"createdAt":"2023-10-09T09:53:45.000Z","salary":{"visible":true,"currency":"IDR","max":"7500000","min":"6000000","period":"monthly"},"company":{"name":"","logo":null,"website":"","phone":null},"career":{"level":"Pegawai (non-manajemen & non-supervisor)","qualifications":["Sarjana (S1)"]},"benefit":[]},{"_rid":"a2561757-e159-4691-a408-ccbb0397dbe4","title":"IT Security Officer","categories":["Komputer/Teknologi Informasi","IT-Admin Jaringan/Sistem/Database"],"type":"Penuh Waktu","url":"https://www.jobstreet.co.id/id/job/it-security-officer-4493353","locations":["Surabaya"],"createdAt":"2023-10-09T09:41:44.000Z","salary":{"visible":false,"currency":"IDR","max":null,"min":null,"period":"monthly"},"company":{"name":"PT. Interaktif Internasional","logo":"https://image-service-cdn.seek.com.au/49d6c560e01f8e2f6c83e1a9d8593424e06fc6ff/ee4dce1061f3f616224767ad58cb2fc751b8d2dc","website":"","phone":null},"career":{"level":"Pegawai (non-manajemen & non-supervisor)","qualifications":["Sarjana (S1)"]},"benefit":["Waktu regular, Senin - Jumat","jamsostek","uniform"]},{"_rid":"0d0047f5-c001-4884-a6ae-8b15cc05a8d9","title":"SAP MM/PM/PS Consultant","categories":["Komputer/Teknologi Informasi","IT-Perangkat Lunak"],"type":"Penuh Waktu","url":"https://www.jobstreet.co.id/id/job/sap-mm-pm-ps-consultant-4493349","locations":["Jakarta Selatan"],"createdAt":"2023-10-09T09:38:53.000Z","salary":{"visible":false,"currency":"IDR","max":null,"min":null,"period":"monthly"},"company":{"name":"PT Mitra Solusi Telematika","logo":"https://image-service-cdn.seek.com.au/9b5f919bd8ffbcaf06c034033d2c53ba0d0ad556/ee4dce1061f3f616224767ad58cb2fc751b8d2dc","website":"","phone":null},"career":{"level":"Supervisor/Koordinator","qualifications":["Sarjana (S1)"]},"benefit":["Asuransi Gigi","Tip","Asuransi kesehatan","Olahraga (contoh: pusat kebugaran)","Parkir","Waktu regular, Senin - Jumat","Bisnis (contoh: Kemeja)","Medical"]},{"_rid":"1aa22f5e-5aaa-4e2f-ad23-69ba7e3e91b7","title":"IT Programmer","categories":["Komputer/Teknologi Informasi","IT-Perangkat Lunak"],"type":"Penuh Waktu","url":"https://www.jobstreet.co.id/id/job/it-programmer-4493325","locations":["Jakarta Pusat"],"createdAt":"2023-10-09T09:30:12.000Z","salary":{"visible":false,"currency":"IDR","max":null,"min":null,"period":"monthly"},"company":{"name":"PT Hasjrat Abadi","logo":"https://image-service-cdn.seek.com.au/2d68a54e6c55f42485b3be436af412d683d8e488/ee4dce1061f3f616224767ad58cb2fc751b8d2dc","website":"","phone":null},"career":{"level":"Pegawai (non-manajemen & non-supervisor)","qualifications":["Sarjana (S1)"]},"benefit":["Asuransi kesehatan","Bisnis (contoh: Kemeja)","Monday - Saturday"]},{"_rid":"619aa542-9dd9-421f-8eb5-31885960b342","title":"Senior Programmer","categories":["Komputer/Teknologi Informasi","IT-Perangkat Lunak"],"type":"Kontrak","url":"https://www.jobstreet.co.id/id/job/senior-programmer-4493320","locations":["Jakarta Pusat"],"createdAt":"2023-10-09T09:29:23.000Z","salary":{"visible":false,"currency":"IDR","max":null,"min":null,"period":"monthly"},"company":{"name":"PT Administrasi Medika","logo":"https://image-service-cdn.seek.com.au/11868c51d35007ab483267732463847817d00f6d/ee4dce1061f3f616224767ad58cb2fc751b8d2dc","website":"","phone":null},"career":{"level":"Manajer/Asisten Manajer","qualifications":["Sarjana (S1)"]},"benefit":["Asuransi Gigi","Asuransi kesehatan","Penglihatan","Waktu regular, Senin - Jumat","Bisnis (contoh: Kemeja)"]},{"_rid":"e62ade16-95e8-4d83-86f8-594a3f70447a","title":"IT Application Support","categories":["Komputer/Teknologi Informasi","IT-Perangkat Lunak"],"type":"Penuh Waktu","url":"https://www.jobstreet.co.id/id/job/it-application-support-4493302","locations":["Surabaya"],"createdAt":"2023-10-09T09:20:29.000Z","salary":{"visible":false,"currency":"IDR","max":null,"min":null,"period":"monthly"},"company":{"name":"PT. Artha Adipersada","logo":"https://image-service-cdn.seek.com.au/79f4dc8cf28ba9e26902992e618fd87ebf0393ac/ee4dce1061f3f616224767ad58cb2fc751b8d2dc","website":"","phone":null},"career":{"level":"Pegawai (non-manajemen & non-supervisor)","qualifications":["Sarjana (S1)"]},"benefit":["Bisnis (contoh: Kemeja)","BPJS & Jamsostek","Monday-Saturday"]},{"_rid":"f06aa131-4e21-436f-8c86-8cefa265c68f","title":"E-Commerce Operations Specialist","categories":["Penjualan / Pemasaran","E-commerce"],"type":"Penuh Waktu","url":"https://www.jobstreet.co.id/id/job/e-commerce-operations-specialist-4493283","locations":["Tangerang"],"createdAt":"2023-10-09T09:12:59.000Z","salary":{"visible":true,"currency":"IDR","max":"5000000","min":"4000000","period":"monthly"},"company":{"name":"PT Noivern Mandiri Indonesia","logo":"https://image-service-cdn.seek.com.au/ce3866452afdd911d980835a7cedc145bec943a1/ee4dce1061f3f616224767ad58cb2fc751b8d2dc","website":"","phone":null},"career":{"level":"Pegawai (non-manajemen & non-supervisor)","qualifications":["Sertifikat Professional","D3 (Diploma)","D4 (Diploma)"]},"benefit":["Tip","Parkir","Jam Bekerja yang Panjang","Bisnis (contoh: Kemeja)","Bonus THR Trasnport Perumahan"]},{"_rid":"a6d5d47f-5fc2-4793-93fe-98b25a3ea46d","title":"Network Engineer","categories":["Komputer/Teknologi Informasi","IT-Admin Jaringan/Sistem/Database"],"type":"Penuh Waktu","url":"https://www.jobstreet.co.id/id/job/network-engineer-4493282","locations":["Gianyar"],"createdAt":"2023-10-09T09:12:03.000Z","salary":{"visible":false,"currency":"IDR","max":null,"min":null,"period":"monthly"},"company":{"name":"Taman Safari Indonesia","logo":"https://image-service-cdn.seek.com.au/94918cbfdaa9fa21687515e4c440706a4f84bf14/ee4dce1061f3f616224767ad58cb2fc751b8d2dc","website":"","phone":null},"career":{"level":"Pegawai (non-manajemen & non-supervisor)","qualifications":["Tidak terspesifikasi"]},"benefit":["Asuransi kesehatan","Waktu regular, Senin - Jumat","Bisnis (contoh: Kemeja)","Bonus"]},{"_rid":"4a4ea8f1-5ca9-483c-8183-67cd21971bd3","title":"DevOps Engineer","categories":["Komputer/Teknologi Informasi","IT-Perangkat Lunak"],"type":"Penuh Waktu","url":"https://www.jobstreet.co.id/id/job/devops-engineer-4493272","locations":["Bandung"],"createdAt":"2023-10-09T09:08:50.000Z","salary":{"visible":true,"currency":"IDR","max":"4500000","min":"3000000","period":"monthly"},"company":{"name":"PT Distributor  Indonesia Unggul","logo":"https://image-service-cdn.seek.com.au/09c95295028ddc475099be3c67f68fa53568e4f5/ee4dce1061f3f616224767ad58cb2fc751b8d2dc","website":"","phone":null},"career":{"level":"Pegawai (non-manajemen & non-supervisor)","qualifications":["Sarjana (S1)"]},"benefit":["Parkir","Waktu regular, Senin - Jumat","Kasual (contoh: Kaos)","BPJS Kesehatan, BPJS Ketenagakerjaan"]},{"_rid":"e0b81277-07af-4f4b-bd99-8f04c46606ae","title":"MANAGEMENT INFORMATION SYSTEM (MIS) ANALYST","categories":["Komputer/Teknologi Informasi","IT-Admin Jaringan/Sistem/Database"],"type":"Penuh Waktu","url":"https://www.jobstreet.co.id/id/job/management-information-system-mis-analyst-4493267","locations":["Jakarta Barat"],"createdAt":"2023-10-09T09:05:53.000Z","salary":{"visible":false,"currency":"IDR","max":null,"min":null,"period":"monthly"},"company":{"name":"PT Mega Central Finance","logo":"https://image-service-cdn.seek.com.au/5a3af6aef73aefc68566a4c26b6f9b36cb214c9e/ee4dce1061f3f616224767ad58cb2fc751b8d2dc","website":"","phone":null},"career":{"level":"Pegawai (non-manajemen & non-supervisor)","qualifications":["Sarjana (S1)"]},"benefit":["Asuransi Gigi","Tunjangan Pendidikan","Tip","Asuransi kesehatan","Pinjaman","Olahraga (contoh: pusat kebugaran)","Parkir","Penglihatan","Waktu regular, Senin - Jumat","Bisnis (contoh: Kemeja)"]},{"_rid":"756b6208-809e-484d-a75c-991c71c35726","title":"Network/System Engineer","categories":["Komputer/Teknologi Informasi","IT-Admin Jaringan/Sistem/Database"],"type":"Penuh Waktu","url":"https://www.jobstreet.co.id/id/job/network-system-engineer-4493248","locations":["Jakarta Barat"],"createdAt":"2023-10-09T08:57:11.000Z","salary":{"visible":true,"currency":"IDR","max":"7500000","min":"5000000","period":"monthly"},"company":{"name":"PT WISESTYLE TRADING INTERNATIONAL","logo":null,"website":"","phone":null},"career":{"level":"Pegawai (non-manajemen & non-supervisor)","qualifications":["Tidak terspesifikasi"]},"benefit":["Waktu regular, Senin - Jumat","Formil (contoh: Kemeja + Dasi)"]},{"_rid":"d70a09a9-d2b5-4363-ad1e-b2d820588fb0","title":"IT Support & Programmer","categories":["Komputer/Teknologi Informasi","IT-Perangkat Lunak"],"type":"Kontrak","url":"https://www.jobstreet.co.id/id/job/it-support-programmer-4493234","locations":["Jawa Timur"],"createdAt":"2023-10-09T08:56:03.000Z","salary":{"visible":false,"currency":"IDR","max":null,"min":null,"period":"monthly"},"company":{"name":"CV. Surya Indo Connection","logo":null,"website":"","phone":null},"career":{"level":"Pegawai (non-manajemen & non-supervisor)","qualifications":["SMA","SMU/SMK/STM","Sertifikat Professional","D3 (Diploma)","D4 (Diploma)","Sarjana (S1)"]},"benefit":["Tip","Bisnis (contoh: Kemeja)","BPJS KETENAGAKERJAAN","Senin - Sabtu"]},{"_rid":"9b72e38b-82a0-45c1-9ba4-b9952129280d","title":"STAFF IT (BEKASI)","categories":["Komputer/Teknologi Informasi","IT-Admin Jaringan/Sistem/Database"],"type":"Penuh Waktu","url":"https://www.jobstreet.co.id/id/job/staff-it-bekasi-4493249","locations":["Bekasi"],"createdAt":"2023-10-09T08:54:51.000Z","salary":{"visible":false,"currency":"IDR","max":null,"min":null,"period":"monthly"},"company":{"name":"PT Multi Arthamas Glass Industry","logo":"https://image-service-cdn.seek.com.au/63c23608a548a9f32ca37b1177f7cf52ab722b8f/ee4dce1061f3f616224767ad58cb2fc751b8d2dc","website":"","phone":null},"career":{"level":"Pegawai (non-manajemen & non-supervisor)","qualifications":["Sertifikat Professional","D3 (Diploma)","D4 (Diploma)","Sarjana (S1)"]},"benefit":["Bisnis (contoh: Kemeja)","-","Monday - Friday : office , Monday - Saturday : operational"]},{"_rid":"0017c73c-5c88-488e-9891-d036fd8754d9","title":"IT Web Developer","categories":["Komputer/Teknologi Informasi","IT-Perangkat Lunak"],"type":"Penuh Waktu","url":"https://www.jobstreet.co.id/id/job/it-web-developer-4493202","locations":["Jakarta Raya"],"createdAt":"2023-10-09T08:37:19.000Z","salary":{"visible":false,"currency":"IDR","max":null,"min":null,"period":"monthly"},"company":{"name":"OZORA PUBLISHING CO., LTD","logo":"https://image-service-cdn.seek.com.au/4ea018b22b5e4389a22e3b97a76960a3537619e1/ee4dce1061f3f616224767ad58cb2fc751b8d2dc","website":"","phone":null},"career":{"level":"Pegawai (non-manajemen & non-supervisor)","qualifications":["Sarjana (S1)"]},"benefit":["Waktu regular, Senin - Jumat","Bisnis (contoh: Kemeja)","Transportation allowance"]},{"_rid":"ab5062e1-f224-4e7f-bc9b-ab9c376bfd12","title":"Devops Engineer","categories":["Komputer/Teknologi Informasi","IT-Perangkat Lunak"],"type":"Penuh Waktu","url":"https://www.jobstreet.co.id/id/job/devops-engineer-4493188","locations":["Jakarta Selatan"],"createdAt":"2023-10-09T08:34:20.000Z","salary":{"visible":true,"currency":"IDR","max":"12000000","min":"9000000","period":"monthly"},"company":{"name":"PT ABISHAR TECHNOLOGIES INDONESIA","logo":"https://image-service-cdn.seek.com.au/a896784d6f6736a8028d861f2d4f16bacf6e4351/ee4dce1061f3f616224767ad58cb2fc751b8d2dc","website":"","phone":null},"career":{"level":"Pegawai (non-manajemen & non-supervisor)","qualifications":["Sarjana (S1)","Diploma Pascasarjana","Gelar Professional","Magister (S2)"]},"benefit":["Asuransi kesehatan","Parkir","Waktu regular, Senin - Jumat","Bisnis (contoh: Kemeja)"]},{"_rid":"203bcc49-f7f0-407c-8cd8-547972017024","title":"SAP Senior Consultant (FICO/MM/PP)","categories":["Komputer/Teknologi Informasi","IT-Perangkat Lunak"],"type":"Penuh Waktu","url":"https://www.jobstreet.co.id/id/job/sap-senior-consultant-fico-mm-pp-11067852/origin/sg","locations":["Jakarta Raya"],"createdAt":"2023-10-09T08:31:32.000Z","salary":{"visible":false,"currency":"IDR","max":null,"min":null,"period":"monthly"},"company":{"name":"Hand Global Solutions Pte. Ltd.","logo":"https://image-service-cdn.seek.com.au/8a8beeb174ace08c12ee151da29bf86f3357af85/ee4dce1061f3f616224767ad58cb2fc751b8d2dc","website":"","phone":null},"career":{"level":"Supervisor/Koordinator","qualifications":["Tidak terspesifikasi"]},"benefit":[]},{"_rid":"ccea5ac0-27fb-43b8-b7db-9d29df5e8904","title":"Data Engineer","categories":["Komputer/Teknologi Informasi","IT-Perangkat Lunak"],"type":"Penuh Waktu","url":"https://www.jobstreet.co.id/id/job/data-engineer-4493164","locations":["Jakarta Pusat"],"createdAt":"2023-10-09T08:25:06.000Z","salary":{"visible":true,"currency":"IDR","max":"18000000","min":"12000000","period":"monthly"},"company":{"name":"PT I Like Gym Indonesia","logo":"https://image-service-cdn.seek.com.au/680f33e799ce61e62b772be88cd7241ac9502e1a/ee4dce1061f3f616224767ad58cb2fc751b8d2dc","website":"","phone":null},"career":{"level":"Pegawai (non-manajemen & non-supervisor)","qualifications":["Sarjana (S1)"]},"benefit":["Tip","Asuransi kesehatan","Bisnis (contoh: Kemeja)","5 working Day"]},{"_rid":"a49b970d-ba0f-4978-8a83-70ec366532db","title":"IT Programmer Officer","categories":["Komputer/Teknologi Informasi","IT-Perangkat Lunak"],"type":"Penuh Waktu","url":"https://www.jobstreet.co.id/id/job/it-programmer-officer-4493156","locations":["Jakarta Raya"],"createdAt":"2023-10-09T08:22:51.000Z","salary":{"visible":false,"currency":"IDR","max":null,"min":null,"period":"monthly"},"company":{"name":"PT Mitsui Leasing Capital Indonesia","logo":"https://image-service-cdn.seek.com.au/1d42ec675881b8ab3a09c7f0f2d5b1bdcb94b986/ee4dce1061f3f616224767ad58cb2fc751b8d2dc","website":"","phone":null},"career":{"level":"Pegawai (non-manajemen & non-supervisor)","qualifications":["Sarjana (S1)"]},"benefit":["Asuransi Gigi","Asuransi kesehatan","Pinjaman","Penglihatan","Waktu regular, Senin - Jumat","Bisnis (contoh: Kemeja)","Personal Accident Insurance"]}]