[{"_rid":"4cbc234d-ab9d-4d38-8e3d-e7f794a96c8e","title":"FULL STACK DEVELOPER","categories":["Komputer/Teknologi Informasi","IT-Perangkat Lunak"],"type":"Penuh Waktu","url":"https://www.jobstreet.co.id/id/job/full-stack-developer-4455747","locations":["Jakarta Pusat"],"createdAt":"2023-09-01T04:46:29.000Z","salary":{"visible":false,"currency":"IDR","max":null,"min":null,"period":"monthly"},"company":{"name":"PT Transforme Indonesia","logo":"https://image-service-cdn.seek.com.au/b175d98cdb44ae2ac5bf7a84c02fbd3f8101edd9/ee4dce1061f3f616224767ad58cb2fc751b8d2dc","website":"","phone":null},"career":{"level":"Pegawai (non-manajemen & non-supervisor)","qualifications":["Sarjana (S1)"]},"benefit":["Asuransi kesehatan","Waktu regular, Senin - Jumat","Kasual (contoh: Kaos)"]},{"_rid":"1005c7ad-5200-4fb4-9c3e-cbd55ae7ea5c","title":"Officer Management Information System (MIS)","categories":["Komputer/Teknologi Informasi","IT-Admin Jaringan/Sistem/Database"],"type":"Penuh Waktu","url":"https://www.jobstreet.co.id/id/job/officer-management-information-system-mis-4455740","locations":["Jakarta Raya"],"createdAt":"2023-09-01T04:44:06.000Z","salary":{"visible":false,"currency":"IDR","max":null,"min":null,"period":"monthly"},"company":{"name":"SINAR ANTJOL GROUP (B29)","logo":"https://image-service-cdn.seek.com.au/2fae777e8eec9a2c406987325a61f9feab1b5262/ee4dce1061f3f616224767ad58cb2fc751b8d2dc","website":"","phone":null},"career":{"level":"Pegawai (non-manajemen & non-supervisor)","qualifications":["Sarjana (S1)","Diploma Pascasarjana","Gelar Professional","Magister (S2)"]},"benefit":["Tunjangan Pendidikan","Asuransi kesehatan","Parkir","Transport, Meal , Allowance, Incentive for Certain Level","Uniform","Mondays-Fridays , Half Saturdays"]},{"_rid":"3b21e626-f70b-4eb5-9673-310b832e8aa8","title":"Full Stack Developer (Yogyakarta)","categories":["Komputer/Teknologi Informasi","IT-Perangkat Lunak"],"type":"Penuh Waktu","url":"https://www.jobstreet.co.id/id/job/full-stack-developer-yogyakarta-4455726","locations":["Yogyakarta"],"createdAt":"2023-09-01T04:36:19.000Z","salary":{"visible":false,"currency":"IDR","max":null,"min":null,"period":"monthly"},"company":{"name":"PT Himalaya Everest Jaya","logo":"https://image-service-cdn.seek.com.au/918057ce7efa9e47b516240b9a1604a6c65ba38c/ee4dce1061f3f616224767ad58cb2fc751b8d2dc","website":"","phone":null},"career":{"level":"Pegawai (non-manajemen & non-supervisor)","qualifications":["Sarjana (S1)"]},"benefit":["Asuransi kesehatan","Waktu regular, Senin - Jumat","Bisnis (contoh: Kemeja)"]},{"_rid":"ed2fedef-b24e-425b-89c1-3a21243c7957","title":"Quality Assurance","categories":["Komputer/Teknologi Informasi","IT-Admin Jaringan/Sistem/Database"],"type":"Penuh Waktu","url":"https://www.jobstreet.co.id/id/job/quality-assurance-4455725","locations":["Tangerang"],"createdAt":"2023-09-01T04:35:52.000Z","salary":{"visible":false,"currency":"IDR","max":null,"min":null,"period":"monthly"},"company":{"name":"PT Multipolar Technology Tbk","logo":"https://image-service-cdn.seek.com.au/fac8ec91dcc0012b551a1f20f6d2707a1f7be282/ee4dce1061f3f616224767ad58cb2fc751b8d2dc","website":"","phone":null},"career":{"level":"Lulusan baru/Pengalaman kerja kurang dari 1 tahun","qualifications":["Sarjana (S1)"]},"benefit":["Waktu regular, Senin - Jumat","Bisnis (contoh: Kemeja)","Based on Company Policy"]},{"_rid":"b1490991-dbf8-41d7-9511-e00f0c73829f","title":"Programmer dan Business intelligence","categories":["Komputer/Teknologi Informasi","IT-Perangkat Lunak"],"type":"Kontrak","url":"https://www.jobstreet.co.id/id/job/programmer-dan-business-intelligence-4455716","locations":["Jakarta Pusat"],"createdAt":"2023-09-01T04:30:09.000Z","salary":{"visible":true,"currency":"IDR","max":"8400000","min":"6000000","period":"monthly"},"company":{"name":"PT Securindo Packatama Indonesia","logo":"https://image-service-cdn.seek.com.au/54fe228d7d33dc3b6dc57f2cafea735c684846df/ee4dce1061f3f616224767ad58cb2fc751b8d2dc","website":"","phone":null},"career":{"level":"Pegawai (non-manajemen & non-supervisor)","qualifications":["Sarjana (S1)"]},"benefit":["Asuransi kesehatan","Waktu regular, Senin - Jumat","uniform"]},{"_rid":"971591d2-ee98-4983-8524-c1c95e2b3a72","title":"Cyber Security / Network Security Engineer","categories":["Komputer/Teknologi Informasi","IT-Admin Jaringan/Sistem/Database"],"type":"Penuh Waktu","url":"https://www.jobstreet.co.id/id/job/cyber-security-network-security-engineer-4455714","locations":["Jakarta Selatan"],"createdAt":"2023-09-01T04:28:58.000Z","salary":{"visible":false,"currency":"IDR","max":null,"min":null,"period":"monthly"},"company":{"name":"PT NEC Indonesia","logo":"https://image-service-cdn.seek.com.au/db8aef93a0ac53ab401fb8976cad0e25732b15df/ee4dce1061f3f616224767ad58cb2fc751b8d2dc","website":"","phone":null},"career":{"level":"Pegawai (non-manajemen & non-supervisor)","qualifications":["Sarjana (S1)"]},"benefit":["Asuransi Gigi","Asuransi kesehatan","Pinjaman","Waktu regular, Senin - Jumat","Bisnis (contoh: Kemeja)"]},{"_rid":"7ca369d6-88d4-414f-ac52-97ed6f218253","title":"Technical Writer","categories":["Komputer/Teknologi Informasi","IT-Perangkat Lunak"],"type":"Kontrak","url":"https://www.jobstreet.co.id/id/job/technical-writer-4455705","locations":["Jakarta Pusat"],"createdAt":"2023-09-01T04:26:20.000Z","salary":{"visible":true,"currency":"IDR","max":"10000000","min":"6000000","period":"monthly"},"company":{"name":"PT. Amalura Multi Dimensi","logo":"https://image-service-cdn.seek.com.au/c7add059dcfe1f578f61ddd89e739e5f7c6f2c10/ee4dce1061f3f616224767ad58cb2fc751b8d2dc","website":"","phone":null},"career":{"level":"Pegawai (non-manajemen & non-supervisor)","qualifications":["Sarjana (S1)"]},"benefit":["Waktu regular, Senin - Jumat","Bisnis (contoh: Kemeja)"]},{"_rid":"b598a725-8177-428f-8864-94753ba7de2d","title":"Analyst Programmer","categories":["Komputer/Teknologi Informasi","IT-Admin Jaringan/Sistem/Database"],"type":"Kontrak","url":"https://www.jobstreet.co.id/id/job/analyst-programmer-4455686","locations":["Jakarta Pusat"],"createdAt":"2023-09-01T04:17:45.000Z","salary":{"visible":true,"currency":"IDR","max":"10000000","min":"7000000","period":"monthly"},"company":{"name":"PT. Amalura Multi Dimensi","logo":"https://image-service-cdn.seek.com.au/37b33e397b5a0394aeebd6f10571b4bb4fc5753b/ee4dce1061f3f616224767ad58cb2fc751b8d2dc","website":"","phone":null},"career":{"level":"Pegawai (non-manajemen & non-supervisor)","qualifications":["Sarjana (S1)"]},"benefit":["Waktu regular, Senin - Jumat","Bisnis (contoh: Kemeja)"]},{"_rid":"2b4f1776-271a-47aa-8377-34f8b3594e35","title":"Programmer","categories":["Komputer/Teknologi Informasi","IT-Perangkat Lunak"],"type":"Penuh Waktu","url":"https://www.jobstreet.co.id/id/job/programmer-4455684","locations":["Medan"],"createdAt":"2023-09-01T04:17:13.000Z","salary":{"visible":false,"currency":"IDR","max":null,"min":null,"period":"monthly"},"company":{"name":"PT Mujur Timber","logo":"https://image-service-cdn.seek.com.au/e0661d31e4104719e06e09ee484fdcbaf220f527/ee4dce1061f3f616224767ad58cb2fc751b8d2dc","website":"","phone":null},"career":{"level":"Pegawai (non-manajemen & non-supervisor)","qualifications":["Sarjana (S1)"]},"benefit":["Kasual (contoh: Kaos)","Perumahan"]},{"_rid":"4134d79f-93d9-49af-90c1-e08e4bad396e","title":"Staf Technical Support","categories":["Komputer/Teknologi Informasi","IT-Admin Jaringan/Sistem/Database"],"type":"Penuh Waktu","url":"https://www.jobstreet.co.id/id/job/staf-technical-support-4455683","locations":["Jakarta Barat"],"createdAt":"2023-09-01T04:16:20.000Z","salary":{"visible":false,"currency":"IDR","max":null,"min":null,"period":"monthly"},"company":{"name":"PT International Chemical Industry","logo":"https://image-service-cdn.seek.com.au/d186ca98961dc8fc552b4dc63bda99aaf940118d/ee4dce1061f3f616224767ad58cb2fc751b8d2dc","website":"","phone":null},"career":{"level":"Pegawai (non-manajemen & non-supervisor)","qualifications":["Sarjana (S1)"]},"benefit":["Tip","Asuransi kesehatan","Waktu regular, Senin - Jumat","Bisnis (contoh: Kemeja)"]},{"_rid":"755248cd-1a0e-4255-9118-6928e28bd5de","title":"E-Commerce (Internship)","categories":["Penjualan / Pemasaran","E-commerce"],"type":"Magang","url":"https://www.jobstreet.co.id/id/job/e-commerce-internship-4455681","locations":["Jakarta Raya"],"createdAt":"2023-09-01T04:15:26.000Z","salary":{"visible":false,"currency":"IDR","max":null,"min":null,"period":"monthly"},"company":{"name":"ZAP Clinic (PT. Zulu Alpha Papa)","logo":"https://image-service-cdn.seek.com.au/ecb83c2db6474fe794c33a515e720ab9327450f5/ee4dce1061f3f616224767ad58cb2fc751b8d2dc","website":"","phone":null},"career":{"level":"Lulusan baru/Pengalaman kerja kurang dari 1 tahun","qualifications":["SMA","SMU/SMK/STM","Sertifikat Professional","D3 (Diploma)","D4 (Diploma)"]},"benefit":["Asuransi Gigi","Tip","Asuransi kesehatan","Penglihatan","Bisnis (contoh: Kemeja)","Head Office, Mondays - Fridays ; Operational, Saturdays or Shift required"]},{"_rid":"b0888eed-7d76-4b9a-9ecf-609617ffef44","title":"Project Leader","categories":["Komputer/Teknologi Informasi","IT-Perangkat Lunak"],"type":"Kontrak","url":"https://www.jobstreet.co.id/id/job/project-leader-4455672","locations":["Jakarta Pusat"],"createdAt":"2023-09-01T04:13:12.000Z","salary":{"visible":true,"currency":"IDR","max":"12000000","min":"7000000","period":"monthly"},"company":{"name":"PT. Amalura Multi Dimensi","logo":"https://image-service-cdn.seek.com.au/37b33e397b5a0394aeebd6f10571b4bb4fc5753b/ee4dce1061f3f616224767ad58cb2fc751b8d2dc","website":"","phone":null},"career":{"level":"Pegawai (non-manajemen & non-supervisor)","qualifications":["Sarjana (S1)"]},"benefit":["Waktu regular, Senin - Jumat","Bisnis (contoh: Kemeja)"]},{"_rid":"6b6e00cd-e695-4e0c-aafc-fe1501011a91","title":"IT Application Development","categories":["Komputer/Teknologi Informasi","IT-Perangkat Lunak"],"type":"Penuh Waktu","url":"https://www.jobstreet.co.id/id/job/it-application-development-4455666","locations":["Jakarta Pusat"],"createdAt":"2023-09-01T04:10:13.000Z","salary":{"visible":false,"currency":"IDR","max":null,"min":null,"period":"monthly"},"company":{"name":"PT Asuransi Tokio Marine Indonesia","logo":"https://image-service-cdn.seek.com.au/dd088a27a9500a0e8ba89a68d9eaa5da5d68cef0/ee4dce1061f3f616224767ad58cb2fc751b8d2dc","website":"","phone":null},"career":{"level":"Supervisor/Koordinator","qualifications":["Sarjana (S1)"]},"benefit":["Tip","Asuransi kesehatan","Pinjaman","Parkir","Waktu regular, Senin - Jumat","Bisnis (contoh: Kemeja)"]},{"_rid":"ec17f131-5c05-4bfc-94bb-3991b035fa0f","title":"Web Developer & Search Engine Optimization (SEO) Staff","categories":["Komputer/Teknologi Informasi","IT-Admin Jaringan/Sistem/Database"],"type":"Penuh Waktu","url":"https://www.jobstreet.co.id/id/job/web-developer-search-engine-optimization-seo-staff-4455623","locations":["Jakarta Utara"],"createdAt":"2023-09-01T03:55:17.000Z","salary":{"visible":false,"currency":"IDR","max":null,"min":null,"period":"monthly"},"company":{"name":"PT Impack Pratama Industri Tbk","logo":"https://image-service-cdn.seek.com.au/e8fa1d1cd1c52b17a7eb81beb1834a425ea2938f/ee4dce1061f3f616224767ad58cb2fc751b8d2dc","website":"","phone":null},"career":{"level":"Pegawai (non-manajemen & non-supervisor)","qualifications":["Sarjana (S1)","Doktor (S3)"]},"benefit":["Waktu regular, Senin - Jumat","Bisnis (contoh: Kemeja)"]},{"_rid":"57b41156-b02d-472d-b5c7-9fcf54c53717","title":"Staff MIS Infrastruktur","categories":["Komputer/Teknologi Informasi","IT-Admin Jaringan/Sistem/Database"],"type":"Penuh Waktu","url":"https://www.jobstreet.co.id/id/job/staff-mis-infrastruktur-4455617","locations":["Jakarta Barat"],"createdAt":"2023-09-01T03:53:46.000Z","salary":{"visible":false,"currency":"IDR","max":null,"min":null,"period":"monthly"},"company":{"name":"SINAR ANTJOL GROUP (B29)","logo":"https://image-service-cdn.seek.com.au/3f9c79e873a3f9760279e2b435242fd84b76f09c/ee4dce1061f3f616224767ad58cb2fc751b8d2dc","website":"","phone":null},"career":{"level":"Pegawai (non-manajemen & non-supervisor)","qualifications":["Sarjana (S1)"]},"benefit":["Tunjangan Pendidikan","Asuransi kesehatan","Parkir","Transport, Meal , Allowance, Incentive for Certain Level","Uniform","Mondays-Fridays , Half Saturdays"]},{"_rid":"782d27c3-836d-4f2e-b2b5-d3b3f709c237","title":"Technical Leader (Software Engineer) - IT Solutions (A-96953)","categories":["Komputer/Teknologi Informasi","IT-Perangkat Lunak"],"type":"Penuh Waktu","url":"https://www.jobstreet.co.id/id/job/technical-leader-software-engineer-it-solutions-a-96953-4455604","locations":["Jakarta Selatan"],"createdAt":"2023-09-01T03:50:37.000Z","salary":{"visible":true,"currency":"IDR","max":"25000000","min":"18000000","period":"monthly"},"company":{"name":"RGF HR Agent Indonesia","logo":"https://image-service-cdn.seek.com.au/d5868152525c083dcbedb1aa22a408e592bdf7d2/ee4dce1061f3f616224767ad58cb2fc751b8d2dc","website":"","phone":null},"career":{"level":"Supervisor/Koordinator","qualifications":["Sarjana (S1)"]},"benefit":["Asuransi kesehatan","Penglihatan","Waktu regular, Senin - Jumat","Bisnis (contoh: Kemeja)"]},{"_rid":"311e37ae-4817-4a09-b58d-149678319083","title":"Senior React Developer","categories":["Komputer/Teknologi Informasi","IT-Perangkat Lunak"],"type":"Penuh Waktu","url":"https://www.jobstreet.co.id/id/job/senior-react-developer-4455548","locations":["Jakarta Raya"],"createdAt":"2023-09-01T03:27:01.000Z","salary":{"visible":false,"currency":"IDR","max":null,"min":null,"period":"monthly"},"company":{"name":"Erajaya Group","logo":"https://image-service-cdn.seek.com.au/1a2c5a4ce6128662ea32374602a92543f60d4144/ee4dce1061f3f616224767ad58cb2fc751b8d2dc","website":"","phone":null},"career":{"level":"Manajer/Asisten Manajer","qualifications":["Sarjana (S1)"]},"benefit":["Asuransi kesehatan","Waktu regular, Senin - Jumat","Bisnis (contoh: Kemeja)","Annual bonus"]},{"_rid":"f61a1fa0-0d2c-4f61-b232-5eefeaa1e401","title":"Java Developer","categories":["Komputer/Teknologi Informasi","IT-Perangkat Lunak"],"type":"Penuh Waktu","url":"https://www.jobstreet.co.id/id/job/java-developer-4455546","locations":["Denpasar","Bandung"],"createdAt":"2023-09-01T03:26:34.000Z","salary":{"visible":false,"currency":"IDR","max":null,"min":null,"period":"monthly"},"company":{"name":"Geekseat","logo":"https://image-service-cdn.seek.com.au/a94166d692fda70a364e9d5191d7ced8a65f1597/ee4dce1061f3f616224767ad58cb2fc751b8d2dc","website":"","phone":null},"career":{"level":"Pegawai (non-manajemen & non-supervisor)","qualifications":["Sertifikat Professional","D3 (Diploma)","D4 (Diploma)","Sarjana (S1)","Diploma Pascasarjana","Gelar Professional","Magister (S2)"]},"benefit":["Tip","Asuransi kesehatan","Kasual (contoh: Kaos)","Mondays - Fridays | 7AM - 4PM or 8AM - 5PM"]},{"_rid":"d8472640-88d9-44bf-8eee-bc0024a4a56c","title":"(Corporate Sales) E-Commerce Officer","categories":["Penjualan / Pemasaran","E-commerce"],"type":"Penuh Waktu","url":"https://www.jobstreet.co.id/id/job/corporate-sales-e-commerce-officer-4455543","locations":["Jakarta Selatan"],"createdAt":"2023-09-01T03:23:09.000Z","salary":{"visible":false,"currency":"IDR","max":null,"min":null,"period":"monthly"},"company":{"name":"PT Central Mega Kencana","logo":"https://image-service-cdn.seek.com.au/9b52fef82892a49f4a34879ca04e63534ac5d07a/ee4dce1061f3f616224767ad58cb2fc751b8d2dc","website":"","phone":null},"career":{"level":"Pegawai (non-manajemen & non-supervisor)","qualifications":["Sarjana (S1)"]},"benefit":["Waktu regular, Senin - Jumat","BPJS, PPH21","Smart Casual"]},{"_rid":"896237de-9917-45a7-83f8-f09c37befb4b","title":"IT Support","categories":["Komputer/Teknologi Informasi","IT-Perangkat Keras"],"type":"Penuh Waktu","url":"https://www.jobstreet.co.id/id/job/it-support-4455541","locations":["Jakarta Raya"],"createdAt":"2023-09-01T03:22:03.000Z","salary":{"visible":false,"currency":"IDR","max":null,"min":null,"period":"monthly"},"company":{"name":"PT Arthagraha General Insurance","logo":"https://image-service-cdn.seek.com.au/7c9f4c4b232a49715397d8404ae570be6cee4e85/ee4dce1061f3f616224767ad58cb2fc751b8d2dc","website":"","phone":null},"career":{"level":"Pegawai (non-manajemen & non-supervisor)","qualifications":["Sertifikat Professional","D3 (Diploma)","D4 (Diploma)","Sarjana (S1)"]},"benefit":["Asuransi kesehatan","Waktu regular, Senin - Jumat","Bisnis (contoh: Kemeja)"]},{"_rid":"0bafacda-4750-4903-b286-02ad56318fbe","title":"Net Developer","categories":["Komputer/Teknologi Informasi","IT-Perangkat Lunak"],"type":"Penuh Waktu","url":"https://www.jobstreet.co.id/id/job/net-developer-4455535","locations":["Jakarta Pusat"],"createdAt":"2023-09-01T03:20:23.000Z","salary":{"visible":false,"currency":"IDR","max":null,"min":null,"period":"monthly"},"company":{"name":"PT Arthagraha General Insurance","logo":"https://image-service-cdn.seek.com.au/fe0e643ee14e11a5542c9d51ca3ac54a634f3956/ee4dce1061f3f616224767ad58cb2fc751b8d2dc","website":"","phone":null},"career":{"level":"Pegawai (non-manajemen & non-supervisor)","qualifications":["Sarjana (S1)"]},"benefit":["Asuransi kesehatan","Waktu regular, Senin - Jumat","Bisnis (contoh: Kemeja)"]},{"_rid":"872e84b7-b1c6-47b4-aa83-3281b7606a77","title":"Business Analyst","categories":["Komputer/Teknologi Informasi","IT-Perangkat Lunak"],"type":"Penuh Waktu","url":"https://www.jobstreet.co.id/id/job/business-analyst-4455508","locations":["Tangerang"],"createdAt":"2023-09-01T03:02:57.000Z","salary":{"visible":false,"currency":"IDR","max":null,"min":null,"period":"monthly"},"company":{"name":"PT GLOBAL LOYALTY INDONESIA","logo":"https://image-service-cdn.seek.com.au/73a8e7ddf5b69487233fbbb3c0f06556b090db98/ee4dce1061f3f616224767ad58cb2fc751b8d2dc","website":"","phone":null},"career":{"level":"Supervisor/Koordinator","qualifications":["Sarjana (S1)"]},"benefit":["Parkir","Waktu regular, Senin - Jumat","Kasual (contoh: Kaos)","BPJS Kesehatan; BPJS Ketenagakerjaan"]},{"_rid":"e236f19d-a5cb-49a2-8319-9e6da06291e9","title":"Cloud Engineer / Cloud Infrastructure Admin","categories":["Komputer/Teknologi Informasi","IT-Admin Jaringan/Sistem/Database"],"type":"Penuh Waktu","url":"https://www.jobstreet.co.id/id/job/cloud-engineer-cloud-infrastructure-admin-4455468","locations":["Jakarta Raya"],"createdAt":"2023-09-01T02:42:24.000Z","salary":{"visible":false,"currency":"IDR","max":null,"min":null,"period":"monthly"},"company":{"name":"PT. Bizani Learning Center","logo":"https://image-service-cdn.seek.com.au/79cc3ebdbcac0b8f8a3033b751a87f300b8d4b17/ee4dce1061f3f616224767ad58cb2fc751b8d2dc","website":"","phone":null},"career":{"level":"Pegawai (non-manajemen & non-supervisor)","qualifications":["Sarjana (S1)"]},"benefit":["Tunjangan Pendidikan","Tip","Olahraga (contoh: pusat kebugaran)","Parkir","Kasual (contoh: Kaos)","Hybrid"]},{"_rid":"38d346db-73f9-4ca5-9b0c-6d7c00314383","title":"IT MIS","categories":["Komputer/Teknologi Informasi","IT-Admin Jaringan/Sistem/Database"],"type":"Penuh Waktu","url":"https://www.jobstreet.co.id/id/job/it-mis-4455459","locations":["Jakarta Barat"],"createdAt":"2023-09-01T02:38:37.000Z","salary":{"visible":false,"currency":"IDR","max":null,"min":null,"period":"monthly"},"company":{"name":"PT Mega Central Finance","logo":"https://image-service-cdn.seek.com.au/5a3af6aef73aefc68566a4c26b6f9b36cb214c9e/ee4dce1061f3f616224767ad58cb2fc751b8d2dc","website":"","phone":null},"career":{"level":"Pegawai (non-manajemen & non-supervisor)","qualifications":["Sarjana (S1)"]},"benefit":["Asuransi Gigi","Tunjangan Pendidikan","Tip","Asuransi kesehatan","Pinjaman","Olahraga (contoh: pusat kebugaran)","Parkir","Penglihatan","Waktu regular, Senin - Jumat","Bisnis (contoh: Kemeja)"]},{"_rid":"3e79170f-459a-4774-a3bf-1260bfe00228","title":"IT DEVELOPER (.Net)","categories":["Komputer/Teknologi Informasi","IT-Perangkat Lunak"],"type":"Penuh Waktu","url":"https://www.jobstreet.co.id/id/job/it-developer-.net-4455456","locations":["Jakarta Barat"],"createdAt":"2023-09-01T02:37:22.000Z","salary":{"visible":false,"currency":"IDR","max":null,"min":null,"period":"monthly"},"company":{"name":"PT Mega Central Finance","logo":"https://image-service-cdn.seek.com.au/5a3af6aef73aefc68566a4c26b6f9b36cb214c9e/ee4dce1061f3f616224767ad58cb2fc751b8d2dc","website":"","phone":null},"career":{"level":"Supervisor/Koordinator","qualifications":["Sarjana (S1)","Diploma Pascasarjana","Gelar Professional","Magister (S2)"]},"benefit":["Asuransi kesehatan","Parkir","Formil (contoh: Kemeja + Dasi)","Head Office: Senin - Jumat"]},{"_rid":"da7f4f9d-61c6-450a-96ec-0ce91f75119f","title":"Front-End Developer (Vue.js)","categories":["Komputer/Teknologi Informasi","IT-Perangkat Lunak"],"type":"Penuh Waktu","url":"https://www.jobstreet.co.id/id/job/front-end-developer-vue.js-4455442","locations":["Jakarta Barat"],"createdAt":"2023-09-01T02:31:00.000Z","salary":{"visible":false,"currency":"IDR","max":null,"min":null,"period":"monthly"},"company":{"name":"Halosis","logo":"https://image-service-cdn.seek.com.au/5a71b8aafb20225f7e25e024091856a0653e4104/ee4dce1061f3f616224767ad58cb2fc751b8d2dc","website":"","phone":null},"career":{"level":"Pegawai (non-manajemen & non-supervisor)","qualifications":["Sarjana (S1)"]},"benefit":["Waktu regular, Senin - Jumat","Kasual (contoh: Kaos)"]},{"_rid":"c9268160-f87a-4377-9add-a74601130097","title":"Software Quality Assurance (Software Tester)","categories":["Komputer/Teknologi Informasi","IT-Perangkat Lunak"],"type":"Penuh Waktu","url":"https://www.jobstreet.co.id/id/job/software-quality-assurance-software-tester-4455414","locations":["Jakarta Barat"],"createdAt":"2023-09-01T02:13:24.000Z","salary":{"visible":false,"currency":"IDR","max":null,"min":null,"period":"monthly"},"company":{"name":"Halosis","logo":"https://image-service-cdn.seek.com.au/5a71b8aafb20225f7e25e024091856a0653e4104/ee4dce1061f3f616224767ad58cb2fc751b8d2dc","website":"","phone":null},"career":{"level":"Pegawai (non-manajemen & non-supervisor)","qualifications":["Sarjana (S1)"]},"benefit":["Waktu regular, Senin - Jumat","Kasual (contoh: Kaos)"]},{"_rid":"31330275-aa40-42c5-b0ab-52e8b23e7830","title":"Data Engineer","categories":["Komputer/Teknologi Informasi","IT-Admin Jaringan/Sistem/Database"],"type":"Kontrak","url":"https://www.jobstreet.co.id/id/job/data-engineer-4455413","locations":["Jakarta Raya"],"createdAt":"2023-09-01T02:13:23.000Z","salary":{"visible":true,"currency":"IDR","max":"14000000","min":"7000000","period":"monthly"},"company":{"name":"PT. PERSOLKELLY Recruitment Indonesia","logo":"https://siva.jsstatic.com/id/1083/images/logo/1083_logo_0_512361.png","website":"","phone":null},"career":{"level":"Pegawai (non-manajemen & non-supervisor)","qualifications":["Sertifikat Professional","D3 (Diploma)","D4 (Diploma)","Sarjana (S1)"]},"benefit":["Asuransi kesehatan","Waktu regular, Senin - Jumat","Bisnis (contoh: Kemeja)"]},{"_rid":"824fb198-76ec-4215-8671-2310829c3e03","title":"Web Administrator + Graphic Designer","categories":["Penjualan / Pemasaran","E-commerce"],"type":"Penuh Waktu","url":"https://www.jobstreet.co.id/id/job/web-administrator-graphic-designer-4455400","locations":["Surabaya"],"createdAt":"2023-09-01T02:06:51.000Z","salary":{"visible":true,"currency":"IDR","max":"3500000","min":"2500000","period":"monthly"},"company":{"name":"Usaha Dagang Setia Budi","logo":"https://image-service-cdn.seek.com.au/dcdfbef08ac8ef16c98cbf41925a15698f6363d2/ee4dce1061f3f616224767ad58cb2fc751b8d2dc","website":"","phone":null},"career":{"level":"Lulusan baru/Pengalaman kerja kurang dari 1 tahun","qualifications":["SMA","SMU/SMK/STM","Sertifikat Professional","D3 (Diploma)","D4 (Diploma)","Sarjana (S1)"]},"benefit":["Kasual (contoh: Kaos)","Monday to Saturday"]},{"_rid":"f0a718af-3e83-42c8-86dd-ec6397b8c1b2","title":"Senior Marketplace Specialist","categories":["Penjualan / Pemasaran","E-commerce"],"type":"Penuh Waktu","url":"https://www.jobstreet.co.id/id/job/senior-marketplace-specialist-4455390","locations":["Tangerang"],"createdAt":"2023-09-01T02:00:37.000Z","salary":{"visible":true,"currency":"IDR","max":"6000000","min":"4000000","period":"monthly"},"company":{"name":"CV KREASI SUKSES MAKMUR","logo":"https://image-service-cdn.seek.com.au/a25642b1f86b576768b5076ec8ea58bfc562f2fd/ee4dce1061f3f616224767ad58cb2fc751b8d2dc","website":"","phone":null},"career":{"level":"Pegawai (non-manajemen & non-supervisor)","qualifications":["SMA","SMU/SMK/STM","Sertifikat Professional","D3 (Diploma)","D4 (Diploma)","Sarjana (S1)"]},"benefit":["Tunjangan Pendidikan","Tip","Asuransi kesehatan","Pinjaman","Kasual (contoh: Kaos)","Jenjang karir, bonus dan cuti tahunan, THR, BPJS","Monday-Saturday"]}]